README.rst
setup.py
dy/__init__.py
dy.fi.egg-info/PKG-INFO
dy.fi.egg-info/SOURCES.txt
dy.fi.egg-info/dependency_links.txt
dy.fi.egg-info/entry_points.txt
dy.fi.egg-info/namespace_packages.txt
dy.fi.egg-info/not-zip-safe
dy.fi.egg-info/requires.txt
dy.fi.egg-info/top_level.txt
dy/fi/__init__.py
dy/fi/ip.txt
dy/fi/docs/LICENSE.rst
dy/fi/tests/__init__.py
dy/fi/tests/test_class.py