Metadata-Version: 1.1
Name: dy.fi
Version: 0.2
Summary: Adds commands to check dynamic IP address change and inform currenty IP address to dy.fi.
Home-page: https://github.com/taito/dy.fi
Author: Taito Horiuchi
Author-email: taito.horiuchi@gmail.com
License: BSD
Platform: UNKNOWN
Classifier: Programming Language :: Python
Classifier: Programming Language :: Python :: 2.7
